pysocket/__init__.py
pysocket/client.py
pysocket/event.py
pysocket/packet.py
pysocket/pysocket.py
pysocket/sk.py
py_socket_io-1.0.2.dist-info/LICENSE
py_socket_io-1.0.2.dist-info/METADATA
py_socket_io-1.0.2.dist-info/WHEEL
py_socket_io-1.0.2.dist-info/top_level.txt
py_socket_io-1.0.2.dist-info/RECORD
