Metadata-Version: 2.1
Name: py-socket-io
Version: 1.0.2
Summary: Python Socket I/O Module
Home-page: UNKNOWN
Author: moonsung
Author-email: dit67890@gmail.com
License: UNKNOWN
Platform: UNKNOWN
Requires-Python: >=3
